htbulma/__init__.py
htbulma/bases.py
htbulma/containers.py
htbulma/containers2.py
htbulma/fields.py
htbulma/fileselect.py
htbulma/fileupload.py
htbulma/form.py
htbulma/inputs.py
htbulma/inputs2.py
htbulma/nav.py
htbulma/services/__init__.py
htbulma/services/clipboard.py
htbulma/services/mbox.py
htbulma/services/popmenu.py
htbulma/services/toaster.py
htbulma/splitters.py
htbulma/table.py
htbulma/tabs.py
htbulma/tags.py
htbulma-0.7.5.dist-info/LICENSE
htbulma-0.7.5.dist-info/WHEEL
htbulma-0.7.5.dist-info/METADATA
htbulma-0.7.5.dist-info/RECORD
