Metadata-Version: 2.1
Name: htbulma
Version: 0.7.5
Summary: GUI toolkit for creating beautiful applications for mobile, web, and desktop from a single python3 codebase
Home-page: https://github.com/manatlan/htbulma
License: MIT
Keywords: htag,gui,electron,cef,pywebview,starlette,tornado,android,apk,asyncio,guy,desktop,web,mobile,http,websocket,html,pyscript
Author: manatlan
Author-email: manatlan@gmail.com
Requires-Python: >=3.7,<4.0
Classifier: License :: OSI Approved :: Apache Software License
Classifier: License :: OSI Approved :: MIT License
Classifier: Operating System :: OS Independent
Classifier: Programming Language :: Python :: 3
Classifier: Programming Language :: Python :: 3.7
Classifier: Programming Language :: Python :: 3.8
Classifier: Topic :: Software Development :: Build Tools
Classifier: Topic :: Software Development :: Libraries :: Python Modules
Requires-Dist: htag (>=0.7,<0.8)
Project-URL: Documentation, https://github.com/manatlan/htbulma
Project-URL: Repository, https://github.com/manatlan/htbulma
